{"_ts":[1590992236],"_r":{"breakdown":{"html":{"bytes":[11258],"requests":[2]},"js":{"bytes":[61821],"requests":[10]},"css":{"bytes":[55089],"requests":[12]},"image":{"bytes":[64532],"requests":[3]},"flash":{"bytes":[0],"requests":[0]},"font":{"bytes":[0],"requests":[0]},"video":{"bytes":[0],"requests":[0]},"other":{"bytes":[2317],"requests":[2]}},"date":[1590992236],"domElements":[360],"domInteractive":[4903],"firstPaint":[4944],"fullyLoaded":[7865],"id":["200601_0K_199d900adac6e8bf3b9f8860fdd24d99"],"loadTime":[4990],"render":[5000],"SpeedIndex":[5000],"TTFB":[4412],"videoFrames":[[{"_i":"ms_000000.jpg","_t":0,"_vc":0},{"_i":"ms_005000.jpg","_t":5000,"_vc":100}]],"visualComplete":[5000],"lighthouse":[null],"pagespeed":[null]}}